MANIFEST.in
README.md
setup.cfg
setup.py
scrapycw/VERSION
scrapycw/__init__.py
scrapycw/cmdline.py
scrapycw/django_manage.py
scrapycw/settings.py
scrapycw.egg-info/PKG-INFO
scrapycw.egg-info/SOURCES.txt
scrapycw.egg-info/dependency_links.txt
scrapycw.egg-info/entry_points.txt
scrapycw.egg-info/requires.txt
scrapycw.egg-info/top_level.txt
scrapycw/commands/__init__.py
scrapycw/commands/crawl.py
scrapycw/commands/init.py
scrapycw/commands/job_stats.py
scrapycw/commands/jobs.py
scrapycw/commands/pause.py
scrapycw/commands/projects.py
scrapycw/commands/server.py
scrapycw/commands/spiders.py
scrapycw/commands/stop.py
scrapycw/commands/unpause.py
scrapycw/commands/version.py
scrapycw/core/__init__.py
scrapycw/core/error_code.py
scrapycw/core/exception.py
scrapycw/core/scrapycw_object.py
scrapycw/helpers/__init__.py
scrapycw/helpers/job.py
scrapycw/helpers/project.py
scrapycw/helpers/spider.py
scrapycw/helpers/version.py
scrapycw/scrapyrewrite/__init__.py
scrapycw/scrapyrewrite/crawler.py
scrapycw/services/__init__.py
scrapycw/services/job.py
scrapycw/services/project.py
scrapycw/services/spider.py
scrapycw/services/version.py
scrapycw/utils/__init__.py
scrapycw/utils/constant.py
scrapycw/utils/exception.py
scrapycw/utils/file_utils.py
scrapycw/utils/json_encoder.py
scrapycw/utils/logger_parser.py
scrapycw/utils/network.py
scrapycw/utils/process.py
scrapycw/utils/response.py
scrapycw/utils/scrapycw.py
scrapycw/utils/slogger.py
scrapycw/utils/telnet.py
scrapycw/web/__init__.py
scrapycw/web/settings.py
scrapycw/web/urls.py
scrapycw/web/wsgi.py
scrapycw/web/app/__init__.py
scrapycw/web/app/apps.py
scrapycw/web/app/models.py
scrapycw/web/app/urls.py
scrapycw/web/app/views.py
scrapycw/web/app/migrations/0001_initial.py
scrapycw/web/app/migrations/__init__.py