Metadata-Version: 1.1
Name: scrapycw
Version: 0.4.3
Summary: 一个web监控scrapy的工具
Home-page: https://github.com/erygreat/scrapycw
Author: erygreat
Author-email: ery991172821@gmail.com
License: BSD
Keywords: Scrapy Web Monitor
Platform: UNKNOWN
Classifier: Development Status :: 3 - Alpha
Classifier: Framework :: Django :: 3.1
Classifier: Framework :: Pytest
Classifier: Framework :: Scrapy
Classifier: License :: OSI Approved :: BSD License
Classifier: Natural Language :: Chinese (Simplified)
Classifier: Operating System :: MacOS
Classifier: Operating System :: Microsoft
Classifier: Operating System :: POSIX :: Linux
Classifier: Programming Language :: Python :: 3
